pynetgear/__init__.py
pynetgear/__main__.py
pynetgear/const.py
pynetgear/helpers.py
pynetgear/router.py
pynetgear-0.10.10.dist-info/LICENSE
pynetgear-0.10.10.dist-info/METADATA
pynetgear-0.10.10.dist-info/WHEEL
pynetgear-0.10.10.dist-info/top_level.txt
pynetgear-0.10.10.dist-info/zip-safe
pynetgear-0.10.10.dist-info/RECORD
