Metadata-Version: 2.1
Name: pynetgear
Version: 0.10.10
Summary: Access Netgear routers using their SOAP API
Home-page: http://github.com/MatMaul/pynetgear
Download-URL: http://github.com/MatMaul/pynetgear/tarball/0.10.10
Author: Paulus Schoutsen
Author-email: Paulus@PaulusSchoutsen.nl
License: MIT
License-File: LICENSE
Requires-Dist: requests >=2.0
